prompt_to_json/__init__.py
prompt_to_json/converter.py
prompt_to_json/schema.py
prompt_to_json-0.1.1.dist-info/licenses/LICENSE
prompt_to_json-0.1.1.dist-info/METADATA
prompt_to_json-0.1.1.dist-info/WHEEL
prompt_to_json-0.1.1.dist-info/top_level.txt
prompt_to_json-0.1.1.dist-info/RECORD
