Metadata-Version: 2.4
Name: prompt-to-json
Version: 0.1.1
Summary: Convert natural language prompts to structured JSON using OpenAI
Author-email: Aadarsh Gaikwad <aadarshgaikwad04@example.com>
License: MIT
Project-URL: Homepage, https://github.com/OpenSoucrce/prompt-to-json
Requires-Python: >=3.8
License-File: LICENSE
Requires-Dist: openai>=1.0.0
Requires-Dist: pydantic>=2.0
Provides-Extra: dev
Requires-Dist: pytest; extra == "dev"
Requires-Dist: pytest-cov; extra == "dev"
Requires-Dist: pre-commit; extra == "dev"
Requires-Dist: mypy; extra == "dev"
Requires-Dist: ruff; extra == "dev"
Requires-Dist: black; extra == "dev"
Dynamic: license-file
